lib2nbdev2/__init__.py
lib2nbdev2/_modidx.py
lib2nbdev2/_nbdev.py
lib2nbdev2/convert.py
lib2nbdev2/generators.py
lib2nbdev2-0.0.3.dist-info/LICENSE
lib2nbdev2-0.0.3.dist-info/METADATA
lib2nbdev2-0.0.3.dist-info/WHEEL
lib2nbdev2-0.0.3.dist-info/entry_points.txt
lib2nbdev2-0.0.3.dist-info/top_level.txt
lib2nbdev2-0.0.3.dist-info/RECORD
