Metadata-Version: 2.1
Name: lib2nbdev2
Version: 0.0.3
Summary: A small library for converting existing libraries and projects to nbdev
Home-page: https://github.com/dmitryhits/lib2nbdev2/tree/main/
Author: Dmitry Hits
Author-email: dmitry.hits@gmail.com
License: Apache Software License 2.0
Keywords: nbdev lib2nbdev2 fastai fastcore
Classifier: Development Status :: 3 - Alpha
Classifier: Intended Audience :: Developers
Classifier: Natural Language :: English
Classifier: Programming Language :: Python :: 3.7
Classifier: Programming Language :: Python :: 3.8
Classifier: Programming Language :: Python :: 3.9
Classifier: Programming Language :: Python :: 3.10
Classifier: License :: OSI Approved :: Apache Software License
Requires-Python: >=3.7
License-File: LICENSE
Requires-Dist: nbdev (>1.1.15)
Requires-Dist: fastprogress (>=1.0.0)
Requires-Dist: fastcore (>=1.3.21)
Requires-Dist: requests (>=2.25.1)
Provides-Extra: dev
